MANIFEST.in
event_view.xml
setup.py
wizard_moodle.xml
./__init__.py
./__openerp__.py
./event_moodle.py
i18n/cs.po
i18n/de.po
i18n/es.po
i18n/event_moodle.pot
i18n/fr.po
i18n/hr.po
i18n/hu.po
i18n/mk.po
i18n/mn.po
i18n/nl.po
i18n/pt.po
i18n/pt_BR.po
i18n/ro.po
i18n/ru.po
i18n/sl.po
i18n/tr.po
i18n/zh_CN.po
images/active_xmlrpc.png
images/enable_webservice.png
images/token.png
openerp_event_moodle.egg-info/PKG-INFO
openerp_event_moodle.egg-info/SOURCES.txt
openerp_event_moodle.egg-info/dependency_links.txt
openerp_event_moodle.egg-info/requires.txt
openerp_event_moodle.egg-info/top_level.txt
security/ir.model.access.csv